prolice/__init__.py
prolice/prolice.py
prolice-0.2.0.dist-info/LICENSE.txt
prolice-0.2.0.dist-info/METADATA
prolice-0.2.0.dist-info/RECORD
prolice-0.2.0.dist-info/WHEEL
prolice-0.2.0.dist-info/entry_points.txt
prolice-0.2.0.dist-info/top_level.txt
