Metadata-Version: 2.1
Name: prolice
Version: 0.2.0
Summary: Command line interface for flashing iCE40HX1K-EVB
Home-page: https://gitlab.com/stefan.mavrodiev/prolice
Author: Stefan Mavrodiev
Author-email: stefan.mavrodiev@gmail.com
Maintainer: Stefan Mavrodiev
Maintainer-email: stefan.mavrodiev@gmail.com
License: UNKNOWN
Platform: UNKNOWN
Classifier: Development Status :: 4 - Beta
Classifier: Environment :: Console
Classifier: Intended Audience :: Developers
Classifier: Intended Audience :: Education
Classifier: Intended Audience :: End Users/Desktop
Classifier: License :: OSI Approved :: GNU General Public License v3 or later (GPLv3+)
Classifier: Operating System :: POSIX :: Linux
Classifier: Programming Language :: Python
Classifier: Programming Language :: Python :: 3 :: Only
Requires-Python: >=3.5
Requires-Dist: pyftdi (>=0.20)
Requires-Dist: pyspiflash (>=0.5)
Requires-Dist: halo
